xOC05
