Metadata-Version: 2.1
Name: xinabox-OC05
Version: 0.0.5
Summary: Solid state relay
Home-page: https://github.com/xinabox/Python-OC05
Author: Luqmaan Baboo
Author-email: luqmaanbaboo@gmail.com
License: UNKNOWN
Platform: UNKNOWN
Classifier: Programming Language :: Python :: 3
Classifier: License :: OSI Approved :: MIT License
Classifier: Operating System :: OS Independent
Requires-Python: >=3.6
